fastapi_easy_crud/__init__.py
fastapi_easy_crud/base_crud.py
fastapi_easy_crud/base_filter.py
fastapi_easy_crud/exceptions.py
fastapi_quick_crud/__init__.py
fastapi_quick_crud/base_crud.py
fastapi_quick_crud/base_filter.py
fastapi_quick_crud/exceptions.py
fastapi_sqlmodel_crud/__init__.py
fastapi_sqlmodel_crud/base_crud.py
fastapi_sqlmodel_crud/base_filter.py
fastapi_sqlmodel_crud/exceptions.py
sqlmodel-fastcrud/__init__.py
sqlmodel-fastcrud/base_crud.py
sqlmodel-fastcrud/base_filter.py
sqlmodel-fastcrud/exceptions.py
sqlmodel_fastapi_crud/__init__.py
sqlmodel_fastapi_crud/base_crud.py
sqlmodel_fastapi_crud/base_filter.py
sqlmodel_fastapi_crud/exceptions.py
sqlmodel_fastapi_crud-0.1.0.dist-info/METADATA
sqlmodel_fastapi_crud-0.1.0.dist-info/WHEEL
sqlmodel_fastapi_crud-0.1.0.dist-info/top_level.txt
sqlmodel_fastapi_crud-0.1.0.dist-info/RECORD
